onebrain/__init__.py
onebrain/exceptions.py
onebrain/version.py
onebrain/api/__init__.py
onebrain/api/client.py
onebrain/entities/__init__.py
onebrain/entities/_onebrain_object.py
onebrain/entities/metric.py
onebrain/tools/__init__.py
onebrain/tools/env.py
onebrain/tools/file_utils.py
onebrain/tools/rest_utils.py
onebrain/tools/sqlite_utils.py
onebrain/tracking/__init__.py
onebrain/tracking/client.py
onebrain/tracking/utils.py
onebrain/tracking/validation.py
onebrain/tracking/registry/__init__.py
onebrain/tracking/registry/abstract_store.py
onebrain/tracking/registry/mq_store.py
onebrain/tracking/registry/prometheus_store.py
onebrain/tracking/registry/rest_store.py
onebrain/tracking/registry/sqlite_store.py
onebrain-0.0.9.dist-info/LICENSE
onebrain-0.0.9.dist-info/METADATA
onebrain-0.0.9.dist-info/WHEEL
onebrain-0.0.9.dist-info/top_level.txt
onebrain-0.0.9.dist-info/RECORD
