Metadata-Version: 2.1
Name: onebrain
Version: 0.0.9
Summary: onebrain sdk in python version
Home-page: https://github.com/OF-OneBrain/onebrain-sdk
Author: onebrain_team
Author-email: 761043617@qq.com
License: MIT
Keywords: onebrain
Platform: UNKNOWN
Classifier: Programming Language :: Python :: 3
Classifier: License :: OSI Approved :: MIT License
Classifier: Operating System :: OS Independent
Requires-Python: >=3.6
